grokui.admin-1.0-py3.11-nspkg.pth
grokui/admin/__init__.py
grokui/admin/applications.py
grokui/admin/configure.zcml
grokui/admin/interfaces.py
grokui/admin/providers.py
grokui/admin/representation.py
grokui/admin/security.py
grokui/admin/server.py
grokui/admin/utilities.py
grokui/admin/views.py
grokui/admin/applications_templates/applications.pt
grokui/admin/server_templates/server.pt
grokui/admin/templates/rename.pt
grokui/admin/tests/__init__.py
grokui/admin/tests/apps.py
grokui/admin/tests/brokenapps.py
grokui/admin/tests/brokenobjs.py
grokui/admin/tests/events.py
grokui/admin/tests/ftesting.zcml
grokui/admin/tests/infoviews.py
grokui/admin/tests/packdatabase.py
grokui/admin/tests/security.py
grokui/admin/tests/server.py
grokui/admin/tests/tests.py
grokui/admin/tests/apackage/__init__.py
grokui/admin/tests/apackage/module1.py
grokui.admin-1.0.dist-info/LICENSE.txt
grokui.admin-1.0.dist-info/METADATA
grokui.admin-1.0.dist-info/WHEEL
grokui.admin-1.0.dist-info/namespace_packages.txt
grokui.admin-1.0.dist-info/top_level.txt
grokui.admin-1.0.dist-info/RECORD
