Metadata-Version: 2.1
Name: grokui.admin
Version: 1.0
Summary: The Grok administration and development UI
Home-page: https://github.com/zopefoundation/grokui.admin
Author: Zope Foundation and Contributors
Author-email: zope-dev@zope.dev
License: ZPL 2.1
Keywords: zope3 grok grokadmin
Classifier: Development Status :: 7 - Inactive
Classifier: Environment :: Web Environment
Classifier: Intended Audience :: Developers
Classifier: License :: OSI Approved :: Zope Public License
Classifier: Programming Language :: Python
Classifier: Programming Language :: Python :: 3
Classifier: Programming Language :: Python :: 3.7
Classifier: Programming Language :: Python :: 3.8
Classifier: Programming Language :: Python :: 3.9
Classifier: Programming Language :: Python :: 3.10
Classifier: Programming Language :: Python :: 3.11
Classifier: Programming Language :: Python :: Implementation :: CPython
Classifier: Natural Language :: English
Classifier: Operating System :: OS Independent
Classifier: Topic :: Internet :: WWW/HTTP
Classifier: Framework :: Zope :: 3
Requires-Python: >=3.7
License-File: LICENSE.txt
Requires-Dist: BTrees
Requires-Dist: ZODB >=5.0
Requires-Dist: grok >=1.10
Requires-Dist: grokcore.site >=1.6.1
Requires-Dist: grokui.base >=0.8.2
Requires-Dist: persistent
Requires-Dist: setuptools
Requires-Dist: z3c.flashmessage
Requires-Dist: zope.applicationcontrol
Requires-Dist: zope.component
Requires-Dist: zope.configuration
Requires-Dist: zope.contentprovider
Requires-Dist: zope.i18nmessageid
Requires-Dist: zope.interface
Requires-Dist: zope.location
Requires-Dist: zope.login
Requires-Dist: zope.schema
Requires-Dist: zope.site
Requires-Dist: zope.size
Requires-Dist: zope.traversing
Provides-Extra: test
Requires-Dist: zc.buildout ; extra == 'test'
Requires-Dist: zope.exceptions ; extra == 'test'
Requires-Dist: zope.fanstatic ; extra == 'test'
Requires-Dist: zope.principalregistry ; extra == 'test'
Requires-Dist: zope.security ; extra == 'test'
Requires-Dist: zope.securitypolicy ; extra == 'test'
Requires-Dist: zope.session ; extra == 'test'
Requires-Dist: zope.testbrowser ; extra == 'test'
Requires-Dist: zope.testing ; extra == 'test'
